legal_citation_parser/__init__.py
legal_citation_parser/analytics.py
legal_citation_parser/canlii_constants.py
legal_citation_parser/canlii_rules.py
legal_citation_parser/citation_parser.py
legal_citation_parser/utils.py
legal_citation_parser-0.5.1.dist-info/LICENSE
legal_citation_parser-0.5.1.dist-info/METADATA
legal_citation_parser-0.5.1.dist-info/WHEEL
legal_citation_parser-0.5.1.dist-info/top_level.txt
legal_citation_parser-0.5.1.dist-info/RECORD
