Metadata-Version: 2.1
Name: legal-citation-parser
Version: 0.5.1
Summary: Extracts metadata from CanLII case citations
Home-page: https://github.com/646e62/legal_citation_parser
Author: Daniel Nathan Booy
Author-email: 444e42@protonmail.com
License: UNKNOWN
Platform: UNKNOWN
License-File: LICENSE
Requires-Dist: python-dotenv
Requires-Dist: requests
